aayush_color/__init__.py
aayush_color/color.py
aayush_color-1.0.1.dist-info/METADATA
aayush_color-1.0.1.dist-info/WHEEL
aayush_color-1.0.1.dist-info/licenses/LICENCE.txt
aayush_color-1.0.1.dist-info/RECORD
