Metadata-Version: 2.1
Name: aayush_color
Version: 1.0.1
Summary: A simple python program to convert a color format to another color format.
Author-email: Aayush Nagpal <aayush.nagpal2022@vitstudent.ac.in>
License-File: LICENCE.txt
Classifier: License :: OSI Approved :: MIT License
Classifier: Operating System :: OS Independent
Classifier: Programming Language :: Python :: 3
Requires-Python: >=3.7
